voiceAtis/VaLogger.py
voiceAtis/__init__.py
voiceAtis/pyuipc.pyd
voiceAtis/voiceAtis.py
voiceAtis/voiceAtisUtil.py
voiceAtis/xpRemoveAtisFreq.py
voiceAtis-0.1.6.dist-info/LICENSE
voiceAtis-0.1.6.dist-info/METADATA
voiceAtis-0.1.6.dist-info/WHEEL
voiceAtis-0.1.6.dist-info/top_level.txt
voiceAtis-0.1.6.dist-info/RECORD
