Metadata-Version: 2.1
Name: voiceAtis
Version: 0.1.6
Summary: Reads an ATIS from IVAO using voice generation.
Home-page: https://github.com/Sowintuu/voiceAtis
Author: Oliver Clemens
Author-email: sowintuu@aol.com
License: UNKNOWN
Platform: UNKNOWN
Classifier: Development Status :: 4 - Beta
Classifier: Environment :: Console
Classifier: Programming Language :: Python :: 2 :: Only
Classifier: License :: OSI Approved :: GNU General Public License v3 (GPLv3)
Classifier: Operating System :: Microsoft :: Windows
Requires-Dist: pyttsx
Requires-Dist: metar
Requires-Dist: aviationFormula
